distkv_ext/knx/__init__.py
distkv_ext/knx/client.py
distkv_ext/knx/mock.py
distkv_ext/knx/model.py
distkv_ext/knx/task.py
distkv_knx-0.11.2.dist-info/METADATA
distkv_knx-0.11.2.dist-info/WHEEL
distkv_knx-0.11.2.dist-info/top_level.txt
distkv_knx-0.11.2.dist-info/zip-safe
distkv_knx-0.11.2.dist-info/RECORD
